{
  "page": {
    "title": "大理洱海",
    "description": "洱海是云南省第二大淡水湖，以\"风花雪月\"四景之一的洱海月闻名，是理想的休闲度假目的地。"
  },
  "hero": {
    "title": "大理洱海",
    "tags": []
  },
  "introduction": "洱海是云南省第二大淡水湖，以\"风花雪月\"四景之一的洱海月闻名，是理想的休闲度假目的地。",
  "sections": [
    {
      "id": "lake",
      "title": "lake",
      "subtitle": "",
      "type": "mixed",
      "content": {
        "description": [
          "洱海位于大理市，是云南省第二大淡水湖。湖面海拔1972米，面积约256平方公里，平均水深10.5米。\n\n洱海形状似人耳，故名洱海。湖水清澈见底，四周苍山环抱，形成\"苍山洱海\"的绝美景观。"
        ],
        "blocks": [
          {
            "type": "description",
            "data": [
              "洱海位于大理市，是云南省第二大淡水湖。湖面海拔1972米，面积约256平方公里，平均水深10.5米。\n\n洱海形状似人耳，故名洱海。湖水清澈见底，四周苍山环抱，形成\"苍山洱海\"的绝美景观。"
            ]
          }
        ]
      }
    },
    {
      "id": "experience",
      "title": "experience",
      "subtitle": "",
      "type": "mixed",
      "content": {
        "columns": [
          {
            "items": [
              "### 环湖骑行",
              "洱海环湖公路约130公里，沿途经过喜洲古镇、双廊、挖色等白族村落。租一辆自行车或电动车，是游览洱海的最佳方式。",
              "### 古镇漫步"
            ]
          }
        ]
      }
    }
  ],
  "version": "v1",
  "lastModified": "2026-07-06 23:32:43"
}